logsnap/__init__.py
logsnap/analyzer.py
logsnap-1.0.0.dist-info/LICENSE
logsnap-1.0.0.dist-info/METADATA
logsnap-1.0.0.dist-info/WHEEL
logsnap-1.0.0.dist-info/entry_points.txt
logsnap-1.0.0.dist-info/top_level.txt
logsnap-1.0.0.dist-info/RECORD
