Metadata-Version: 2.1
Name: logsnap
Version: 1.0.0
Summary: A simple log file analyzer with summary and search functionality.
Home-page: https://github.com/ibrahimhasnat/logsnap/
Author: Ibrahim Hasnat
License: UNKNOWN
Platform: UNKNOWN
Requires-Python: >=3.6
License-File: LICENSE
Requires-Dist: colorama
